README.rst
setup.py
bash/__init__.py
bash.egg-info/PKG-INFO
bash.egg-info/SOURCES.txt
bash.egg-info/dependency_links.txt
bash.egg-info/top_level.txt